HermesNetwork/__init__.py
HermesNetwork/core.py
HermesNetwork_gabriel_oliveira-4.dev0.dist-info/DESCRIPTION.rst
HermesNetwork_gabriel_oliveira-4.dev0.dist-info/METADATA
HermesNetwork_gabriel_oliveira-4.dev0.dist-info/RECORD
HermesNetwork_gabriel_oliveira-4.dev0.dist-info/WHEEL
HermesNetwork_gabriel_oliveira-4.dev0.dist-info/metadata.json
HermesNetwork_gabriel_oliveira-4.dev0.dist-info/top_level.txt
