Metadata-Version: 2.0
Name: HermesNetwork-gabriel-oliveira
Version: 4.dev0
Summary: A high speed networks system
Home-page: https://test.pypi.org/legacy/
Author: Gabriel De Oliveira
Author-email: gabriel.oli01001@gmail.com
License: UNKNOWN
Platform: UNKNOWN
Classifier: Programming Language :: Python :: 3
Classifier: License :: OSI Approved :: MIT License
Classifier: Operating System :: OS Independent
Requires-Python: >=3.6
